verilog/abba/MealyConDelay/omega-delay.v
module omega(output z, input [1:2]s, input [1:2]x);

  assign
    #1 z = s[1] & ~s[2] & ~x[1] & ~x[2];

endmodule

verilog/abba/MealyConDelay/sigma-delay.v
module sigma(output  [1:2]news, input  [1:2]s, input  [1:2]x);

  assign
    #1 news[1] = s[2] & ~x[1] & x[2];

  assign	
    #2 news[2] = ~s[1] & ~x[1] & ~x[2] 
		 | s[2] & ~x[1] & ~x[2] 
		 | ~s[1] & s[2] & ~x[1];
   
endmodule

verilog/abba/MealyConDelay/reg-delay.v
module registro(output [1:N]stato, input clock, input  enable, input  [1:N]inval);

   parameter N = 2;

   reg [1:N] st;
   
   initial
     begin
	st = 0;
     end
   
   always @(posedge clock)
     begin
	if(enable) 
	  st <= inval;
     end

   assign
     #1 stato = st;
   
endmodule

verilog/abba/MealyConDelay/m1-delay.v
module m1(output  z, input [1:2]x, input clock);

   wire [1:2]outreg;
   wire [1:2]inreg;

   registro s(outreg, clock, 1'b1, inreg);
   sigma sm(inreg, outreg, x);
   omega om(z, outreg, x);
   
endmodule

verilog/abba/MealyConDelay/test-m1-delay.v
module testm1();

   reg [1:2] x;
   reg       clock;
   wire z;
   
   m1 m(z, x, clock);

   initial
     clock = 0;

   // ciclo di clock tau = 4 (leggermente piu' grande del necessario (3))
   always
     begin
	// funz
	#3 clock = 1;
	// non funz
	//#1 clock = 1;
	
	#1 clock = 0;
     end
   
   initial
     begin
	$dumpfile("test-mealy-delay.vcd");
	$dumpvars;

	x = 2'b00;
	#4 x = 2'b01;
	//#4 fa aba e non da' mai 1
	//#8 fa abba e mi da' l'uno
	// se metto il clock a 2 (1+1) non funziona piu'
        #8  x = 2'b01;
	// col clock a 1+1 non funz
	//#5 x = 2'b01;
	
	#1 x = 2'b00;
	
	
	#10 $finish;
     end
endmodule // testm1

verilog/abba/MealyConDelay/test.vcd
$date
	Thu Oct 10 11:35:56 2019
$end
$version
	Icarus Verilog
$end
$timescale
	1s
$end
$scope module testm1 $end
$var wire 1 ! z $end
$var reg 1 " clock $end
$var reg 2 # x [1:2] $end
$scope module m $end
$var wire 1 " clock $end
$var wire 2 $ x [1:2] $end
$var wire 1 ! z $end
$var wire 2 % outreg [1:2] $end
$var wire 2 & inreg [1:2] $end
$scope module om $end
$var wire 2 ' x [1:2] $end
$var wire 1 ! z $end
$var wire 2 ( s [1:2] $end
$upscope $end
$scope module s $end
$var wire 1 " clock $end
$var wire 1 ) enable $end
$var wire 2 * stato [1:2] $end
$var wire 2 + inval [1:2] $end
$var reg 2 , st [1:2] $end
$upscope $end
$scope module sm $end
$var wire 2 - s [1:2] $end
$var wire 2 . x [1:2] $end
$var wire 2 / news [1:2] $end
$upscope $end
$upscope $end
$upscope $end
$enddefinitions $end
#0
$dumpvars
bx /
b0 .
bx -
b0 ,
bx +
bx *
1)
bx (
b0 '
bx &
bx %
b0 $
b0 #
0"
x!
$end
#1
b0x &
b0x +
b0x /
b0 %
b0 (
b0 *
b0 -
#2
0!
#3
b1 ,
b1 &
b1 +
b1 /
1"
#4
b1 %
b1 (
b1 *
b1 -
0"
b1 #
b1 $
b1 '
b1 .
#5
b11 &
b11 +
b11 /
#7
b11 ,
1"
#8
b11 %
b11 (
b11 *
b11 -
0"
#10
b10 &
b10 +
b10 /
#11
b10 ,
1"
#12
b10 %
b10 (
b10 *
b10 -
0"
#13
b0 &
b0 +
b0 /
b0 #
b0 $
b0 '
b0 .
#14
1!
#15
b0 ,
1"
#16
b0 %
b0 (
b0 *
b0 -
0"
#17
0!
#18
b1 &
b1 +
b1 /
#19
b1 ,
1"
#20
b1 %
b1 (
b1 *
b1 -
0"
