verilog/abba/MealyConDelay/omega-delay.v
module omega(output z, input [1:2]s, input [1:2]x);

  assign
    #1 z = s[1] & ~s[2] & ~x[1] & ~x[2];

endmodule

verilog/abba/MealyInSync/sigma.v
module sigma(output  [1:2]news, input  [1:2]s, input  [1:2]x);

  assign
    news[1] = s[2] & ~x[1] & x[2];

  assign	
    news[2] = ~s[1] & ~x[1] & ~x[2] 
	      | s[2] & ~x[1] & ~x[2] 
	      | ~s[1] & s[2] & ~x[1];
   
endmodule

verilog/abba/MealyInSync/reg.v
module registro(output [1:N]z, input clock, input  enable, input  [1:N]inval);

   parameter N = 2;

   reg [1:N] stato;
   
   initial
     begin
	stato = 0;
     end
   
   always @(posedge clock)
     begin
	if(enable) 
	  stato <= inval;
     end

   assign
     z = stato;
   
endmodule

verilog/abba/Mealy/m1.v
module m1(output z, input [1:2]x, input clock);

   wire [1:2]outreg;
   wire [1:2]inreg;

   registro s(outreg, clock, 1'b1, inreg);
   sigma sm(inreg, outreg, x);
   omega om(z, outreg, x);
   
endmodule

verilog/abba/Mealy/test-m1.v
module testm1();

   reg [1:2] x;
   reg       clock;
   wire z;
   
   m1 m(z, x, clock);

   initial
     clock = 0;
   
   always
     begin
	#2 clock = 1;
	#1 clock = 0;
     end
   
   initial
     begin
	$dumpfile("test-mealy.vcd");
	$dumpvars;

	x = 2'b00;
	#4 x = 2'b01;
	#5 x = 2'b01;
	#1 x = 2'b00;
	
	
	#10 $finish;
     end
endmodule // testm1

verilog/abba/Mealy/test.vcd
$date
	Thu Oct 10 11:28:34 2019
$end
$version
	Icarus Verilog
$end
$timescale
	1s
$end
$scope module testm1 $end
$var wire 1 ! z $end
$var reg 1 " clock $end
$var reg 2 # x [1:2] $end
$scope module m $end
$var wire 1 " clock $end
$var wire 2 $ x [1:2] $end
$var wire 1 ! z $end
$var wire 2 % outreg [1:2] $end
$var wire 2 & inreg [1:2] $end
$scope module om $end
$var wire 2 ' x [1:2] $end
$var wire 1 ! z $end
$var wire 2 ( s [1:2] $end
$upscope $end
$scope module s $end
$var wire 1 " clock $end
$var wire 1 ) enable $end
$var wire 2 * z [1:2] $end
$var wire 2 + inval [1:2] $end
$var reg 2 , stato [1:2] $end
$upscope $end
$scope module sm $end
$var wire 2 - s [1:2] $end
$var wire 2 . x [1:2] $end
$var wire 2 / news [1:2] $end
$upscope $end
$upscope $end
$upscope $end
$enddefinitions $end
#0
$dumpvars
b1 /
b0 .
b0 -
b0 ,
b1 +
b0 *
1)
b0 (
b0 '
b1 &
b0 %
b0 $
b0 #
0"
0!
$end
#2
b1 %
b1 (
b1 *
b1 ,
b1 -
1"
#3
0"
#4
b11 &
b11 +
b11 /
b1 #
b1 $
b1 '
b1 .
#5
b10 &
b10 +
b10 /
b11 %
b11 (
b11 *
b11 ,
b11 -
1"
#6
0"
#8
b0 &
b0 +
b0 /
b10 %
b10 (
b10 *
b10 ,
b10 -
1"
#9
0"
#10
1!
b0 #
b0 $
b0 '
b0 .
#11
b1 &
b1 +
b1 /
0!
b0 %
b0 (
b0 *
b0 ,
b0 -
1"
#12
0"
#14
b1 %
b1 (
b1 *
b1 ,
b1 -
1"
