verilog/abba/MealyInSync/reg.v
module registro(output [1:N]z, input clock, input  enable, input  [1:N]inval);

   parameter N = 2;

   reg [1:N] stato;
   
   initial
     begin
	stato = 0;
     end
   
   always @(posedge clock)
     begin
	if(enable) 
	  stato <= inval;
     end

   assign
     z = stato;
   
endmodule

verilog/abba/Moore/mo-omega.v
module omega(output z, input [1:3]s, input [1:2]x);
  // z = 1 solo se ci troviamo nello stato 5 (100)
  assign
    z = s[1]& ~s[2] &~s[3];
   

endmodule

verilog/abba/Moore/mo-sigma.v
module sigma(output [1:3]t, input [1:3]s, input [1:2]x);
   // s[1] & s[2] & s[3] & x[1] & x[2]
   assign
     t[1] = ~s[1] & s[2] & s[3] & ~x[1] & ~x[2];
   assign
     t[2] = ~s[1] & ~s[2] & s[3] & ~x[1] & x[2] |
	    ~s[1] & s[2] & ~x[1] & x[2];
   assign
     t[3] = ~s[1] & ~s[2] & ~x[1] & ~x[2] |
	    ~s[1] & s[2] & ~s[3] & ~x[1]  |
	     s[1] & ~s[2] & ~s[3] & ~x[1] & x[2];
endmodule

verilog/abba/Moore/moore.v
module m1(output z, input [1:2]x , input clock);

   wire [1:3]sinp;
   wire [1:3]sout;

   sigma sm(sinp, sout, x);
   omega om(z, sout, x);
   registro #(3) rs(sout, clock, 1'b1, sinp);
   
   
endmodule

verilog/abba/Moore/test-m1.v
module testm1();

   reg [1:2] x;
   reg       clock;
   wire z;
   
   m1 m(z, x, clock);

   initial
     clock = 0;
   
   always
     begin
	#2 clock = 1;
	#1 clock = 0;
     end
   
   initial
     begin
	$dumpfile("test-moore.vcd");
	$dumpvars;

	x = 2'b00;
	#4 x = 2'b01;
	#5 x = 2'b01;
	#1 x = 2'b00;
	
	
	#10 $finish;
     end
endmodule // testm1

verilog/abba/Moore/test-moore.vcd
$date
	Thu Oct 10 11:43:46 2019
$end
$version
	Icarus Verilog
$end
$timescale
	1s
$end
$scope module testm1 $end
$var wire 1 ! z $end
$var reg 1 " clock $end
$var reg 2 # x [1:2] $end
$scope module m $end
$var wire 1 " clock $end
$var wire 2 $ x [1:2] $end
$var wire 1 ! z $end
$var wire 3 % sout [1:3] $end
$var wire 3 & sinp [1:3] $end
$scope module om $end
$var wire 2 ' x [1:2] $end
$var wire 1 ! z $end
$var wire 3 ( s [1:3] $end
$upscope $end
$scope module rs $end
$var wire 1 " clock $end
$var wire 1 ) enable $end
$var wire 3 * z [1:3] $end
$var wire 3 + inval [1:3] $end
$var reg 3 , stato [1:3] $end
$upscope $end
$scope module sm $end
$var wire 3 - s [1:3] $end
$var wire 2 . x [1:2] $end
$var wire 3 / t [1:3] $end
$upscope $end
$upscope $end
$upscope $end
$enddefinitions $end
#0
$dumpvars
b1 /
b0 .
b0 -
b0 ,
b1 +
b0 *
1)
b0 (
b0 '
b1 &
b0 %
b0 $
b0 #
0"
0!
$end
#2
b1 %
b1 (
b1 *
b1 ,
b1 -
1"
#3
0"
#4
b10 &
b10 +
b10 /
b1 #
b1 $
b1 '
b1 .
#5
b11 &
b11 +
b11 /
b10 %
b10 (
b10 *
b10 ,
b10 -
1"
#6
0"
#8
b10 &
b10 +
b10 /
b11 %
b11 (
b11 *
b11 ,
b11 -
1"
#9
0"
#10
b100 &
b100 +
b100 /
b0 #
b0 $
b0 '
b0 .
#11
b0 &
b0 +
b0 /
1!
b100 %
b100 (
b100 *
b100 ,
b100 -
1"
#12
0"
#14
b1 &
b1 +
b1 /
0!
b0 %
b0 (
b0 *
b0 ,
b0 -
1"
#15
0"
#17
b1 %
b1 (
b1 *
b1 ,
b1 -
1"
