verilog/homework/potenzadidue/potenzadidue.v
module potenzadidue(output z, input [0:N-1]x);
    parameter N = 8;

    assign
        z = (x & (x-1)) == 0 ;
endmodule //potenzadidue

verilog/homework/potenzadidue/test.v
module test();
    reg [0:7] x;
    wire z;

    potenzadidue p (z, x);

    initial
        begin
            $dumpfile("test.vcd");
            $dumpvars;

            x = 8'b10000000; // z = 1
            #1 x = 8'b01000000; // z = 1
            #1 x = 8'b00100000; // z = 1
            #1 x = 8'b00010000; // z = 1
            #1 x = 8'b00001000; // z = 1
            #1 x = 8'b00000100; // z = 1
            #1 x = 8'b00000010; // z = 1
            #1 x = 8'b00000001; // z = 1
            #1 x = 8'b01010010; // z = 0
            #1 x = 8'b01011010; // z = 0
            #1 x = 8'b01000001; // z = 0
            #1 x = 8'b11010000; // z = 0
            #1 x = 8'b10110110; // z = 0
        end
endmodule //test

verilog/homework/potenzadidue/test.vcd
$date
	Fri Oct 25 17:26:33 2019
$end
$version
	Icarus Verilog
$end
$timescale
	1s
$end
$scope module test $end
$var wire 1 ! z $end
$var reg 8 " x [0:7] $end
$scope module p $end
$var wire 8 # x [0:7] $end
$var wire 1 ! z $end
$upscope $end
$upscope $end
$enddefinitions $end
#0
$dumpvars
b10000000 #
b10000000 "
1!
$end
#1
b1000000 "
b1000000 #
#2
b100000 "
b100000 #
#3
b10000 "
b10000 #
#4
b1000 "
b1000 #
#5
b100 "
b100 #
#6
b10 "
b10 #
#7
b1 "
b1 #
#8
0!
b1010010 "
b1010010 #
#9
b1011010 "
b1011010 #
#10
b1000001 "
b1000001 #
#11
b11010000 "
b11010000 #
#12
b10110110 "
b10110110 #
