verilog/abba/MealyInSync/omega.v
module omega(output z, input [1:2]s, input [1:2]x);

  assign
    z = s[1] & ~s[2] & ~x[1] & ~x[2];

endmodule

verilog/abba/MealyInSync/sigma.v
module sigma(output  [1:2]news, input  [1:2]s, input  [1:2]x);

  assign
    news[1] = s[2] & ~x[1] & x[2];

  assign	
    news[2] = ~s[1] & ~x[1] & ~x[2] 
	      | s[2] & ~x[1] & ~x[2] 
	      | ~s[1] & s[2] & ~x[1];
   
endmodule

verilog/abba/MealyInSync/reg.v
module registro(output [1:N]z, input clock, input  enable, input  [1:N]inval);

   parameter N = 2;

   reg [1:N] stato;
   
   initial
     begin
	stato = 0;
     end
   
   always @(posedge clock)
     begin
	if(enable) 
	  stato <= inval;
     end

   assign
     z = stato;
   
endmodule

verilog/abba/MealyInSync/m1.v
module m1(output z, input [1:2]x, input clock);

   wire [1:2] outreg;
   wire [1:2] inreg;
   wire [1:2] xsy;
   
   registro #(2) r(xsy, clock, 1'b1, x);

   registro #(2) s(outreg, clock, 1'b1, inreg);
   sigma sm(inreg, outreg, xsy);
   omega om(z, outreg, xsy);
   
   
endmodule

verilog/abba/MealyConDelay/test-m1-delay.v
module testm1();

   reg [1:2] x;
   reg       clock;
   wire z;
   
   m1 m(z, x, clock);

   initial
     clock = 0;

   // ciclo di clock tau = 4 (leggermente piu' grande del necessario (3))
   always
     begin
	// funz
	#3 clock = 1;
	// non funz
	//#1 clock = 1;
	
	#1 clock = 0;
     end
   
   initial
     begin
	$dumpfile("test-mealy-delay.vcd");
	$dumpvars;

	x = 2'b00;
	#4 x = 2'b01;
	//#4 fa aba e non da' mai 1
	//#8 fa abba e mi da' l'uno
	// se metto il clock a 2 (1+1) non funziona piu'
        #8  x = 2'b01;
	// col clock a 1+1 non funz
	//#5 x = 2'b01;
	
	#1 x = 2'b00;
	
	
	#10 $finish;
     end
endmodule // testm1

verilog/abba/MealyInSync/test-mealy.vcd
$date
	Thu Oct 10 11:40:39 2019
$end
$version
	Icarus Verilog
$end
$timescale
	1s
$end
$scope module testm1 $end
$var wire 1 ! z $end
$var reg 1 " clock $end
$var reg 2 # x [1:2] $end
$scope module m $end
$var wire 1 " clock $end
$var wire 2 $ x [1:2] $end
$var wire 1 ! z $end
$var wire 2 % xsy [1:2] $end
$var wire 2 & outreg [1:2] $end
$var wire 2 ' inreg [1:2] $end
$scope module om $end
$var wire 1 ! z $end
$var wire 2 ( x [1:2] $end
$var wire 2 ) s [1:2] $end
$upscope $end
$scope module r $end
$var wire 1 " clock $end
$var wire 1 * enable $end
$var wire 2 + inval [1:2] $end
$var wire 2 , z [1:2] $end
$var reg 2 - stato [1:2] $end
$upscope $end
$scope module s $end
$var wire 1 " clock $end
$var wire 1 . enable $end
$var wire 2 / z [1:2] $end
$var wire 2 0 inval [1:2] $end
$var reg 2 1 stato [1:2] $end
$upscope $end
$scope module sm $end
$var wire 2 2 s [1:2] $end
$var wire 2 3 x [1:2] $end
$var wire 2 4 news [1:2] $end
$upscope $end
$upscope $end
$upscope $end
$enddefinitions $end
#0
$dumpvars
b1 4
b0 3
b0 2
b0 1
b1 0
b0 /
1.
b0 -
b0 ,
b0 +
1*
b0 )
b0 (
b1 '
b0 &
b0 %
b0 $
b0 #
0"
0!
$end
#2
b1 &
b1 )
b1 /
b1 1
b1 2
1"
#3
0"
#4
b1 #
b1 $
b1 +
#5
b11 '
b11 0
b11 4
b1 %
b1 (
b1 ,
b1 -
b1 3
1"
#6
0"
#8
b10 '
b10 0
b10 4
b11 &
b11 )
b11 /
b11 1
b11 2
1"
#9
0"
#10
b0 #
b0 $
b0 +
#11
1!
b0 '
b0 0
b0 4
b10 &
b10 )
b10 /
b10 1
b10 2
b0 %
b0 (
b0 ,
b0 -
b0 3
1"
#12
0"
#14
b1 '
b1 0
b1 4
0!
b0 &
b0 )
b0 /
b0 1
b0 2
1"
#15
0"
#17
b1 &
b1 )
b1 /
b1 1
b1 2
1"
