verilog/homework/contauguali/counter.v
module counter(
    input inc,
    input clock,
    output [0:N-1] z
);
    parameter N = 8;

    reg [0:N-1] value;

    initial
        value = 0;

    always @(posedge clock) begin
        value = value + inc;
    end

    assign
        z = value;

endmodule // counter

verilog/homework/contauguali/sigma.v
module sigma (
    input [0:M-1] x,
    input [0:M-1] y,
    output inc
);
    parameter M = 8;

    assign
        inc = x[M-1] == y[M-1];
endmodule // sigma

verilog/homework/contauguali/automata.v
module automata (
    input [0:M-1] x,
    input [0:M-1] y,
    input clock,
    output [0:N-1] z
);
    parameter N = 8;
    parameter M = 8;

    wire inc;
    sigma sm(x, y, inc);
    counter c(inc, clock, z);
endmodule // automata

verilog/homework/contauguali/test.v
module test();

   reg [0:7] x;
   reg [0:7] y;
   wire [0:7] z;
   reg clock;

   automata a(x, y, clock, z);

   initial
     clock = 0;
   
   always
     begin
	    #2 clock = 1;
	    #1 clock = 0;
     end
   
   initial
     begin
	    $dumpfile("test.vcd");
	    $dumpvars;

	    x = 3;
	    y = 5;
	    #3 x = 2;
	    y = 3;
        #3 x = 3;
        #3 x = 1;
        #3 x = 2;
        y = 2;

	    #10 $finish;
     end
endmodule // test

verilog/homework/contauguali/test.vcd
$date
	Fri Oct 25 20:28:39 2019
$end
$version
	Icarus Verilog
$end
$timescale
	1s
$end
$scope module test $end
$var wire 8 ! z [0:7] $end
$var reg 1 " clock $end
$var reg 8 # x [0:7] $end
$var reg 8 $ y [0:7] $end
$scope module a $end
$var wire 1 " clock $end
$var wire 8 % x [0:7] $end
$var wire 8 & y [0:7] $end
$var wire 8 ' z [0:7] $end
$var wire 1 ( inc $end
$scope module c $end
$var wire 1 " clock $end
$var wire 8 ) z [0:7] $end
$var wire 1 ( inc $end
$var reg 8 * value [0:7] $end
$upscope $end
$scope module sm $end
$var wire 1 ( inc $end
$var wire 8 + x [0:7] $end
$var wire 8 , y [0:7] $end
$upscope $end
$upscope $end
$upscope $end
$enddefinitions $end
#0
$dumpvars
b101 ,
b11 +
b0 *
b0 )
1(
b0 '
b101 &
b11 %
b101 $
b11 #
0"
b0 !
$end
#2
b1 !
b1 '
b1 )
b1 *
1"
#3
0(
0"
b11 $
b11 &
b11 ,
b10 #
b10 %
b10 +
#5
1"
#6
1(
0"
b11 #
b11 %
b11 +
#8
b10 !
b10 '
b10 )
b10 *
1"
#9
0"
b1 #
b1 %
b1 +
#11
b11 !
b11 '
b11 )
b11 *
1"
#12
0"
b10 $
b10 &
b10 ,
b10 #
b10 %
b10 +
#14
b100 !
b100 '
b100 )
b100 *
1"
#15
0"
#17
b101 !
b101 '
b101 )
b101 *
1"
#18
0"
#20
b110 !
b110 '
b110 )
b110 *
1"
